[
	{
		"p1" : "不规则下摆绑腰带连衣裙",
		"p2" : "收腰显瘦·层析丰富",
		"src" : "shop_1.jpg",
		"price" : "￥199"
	},
	{
		"p1" : "荷叶边七分袖V领套头小衫",
		"p2" : "撞色荷叶边·亲肤面料",
		"src" : "shop_2.jpg",
		"price" : "￥169"
	},
	{
		"p1" : "荷叶边七分袖V领套头小衫",
		"p2" : "撞色荷叶边·亲肤面料",
		"src" : "shop_3.jpg",
		"price" : "￥199"
	},
	{
		"p1" : "荷叶边七分袖V领套头小衫",
		"p2" : "撞色荷叶边·亲肤面料",
		"src" : "shop_4.jpg",
		"price" : "￥169"
	},
	{
		"p1" : "荷叶边七分袖V领套头小衫",
		"p2" : "撞色荷叶边·亲肤面料",
		"src" : "shop_5.jpg",
		"price" : "￥260"
	},
	{
		"p1" : "荷叶边七分袖V领套头小衫",
		"p2" : "撞色荷叶边·亲肤面料",
		"src" : "shop_6.jpg",
		"price" : "￥199"
	},
	{
		"p1" : "荷叶边七分袖V领套头小衫",
		"p2" : "撞色荷叶边·亲肤面料",
		"src" : "shop_7.jpg",
		"price" : "￥499"
	},
	{
		"p1" : "荷叶边七分袖V领套头小衫",
		"p2" : "撞色荷叶边·亲肤面料",
		"src" : "shop_8.jpg",
		"price" : "￥69"
	},
]